lsnms/__init__.py
lsnms/nms.py
lsnms/rtree.py
lsnms/util.py
lsnms/wbc.py
lsnms-0.4.5.dist-info/METADATA
lsnms-0.4.5.dist-info/WHEEL
lsnms-0.4.5.dist-info/RECORD
