Metadata-Version: 2.4
Name: lsnms
Version: 0.4.5
Summary: Large Scale Non Maximum Suppression
License: MIT
Keywords: NMS,Non Maximum Suppression,Histology image,Satellite images,Object detection
Author: Rémy Dubois
Author-email: remydubois14@gmail.com
Requires-Python: >=3.10,<3.14
Classifier: License :: OSI Approved :: MIT License
Classifier: Programming Language :: Python :: 3
Classifier: Programming Language :: Python :: 3.10
Classifier: Programming Language :: Python :: 3.11
Classifier: Programming Language :: Python :: 3.12
Classifier: Programming Language :: Python :: 3.13
Classifier: Topic :: Scientific/Engineering
Requires-Dist: numba (>=0.63.1,<0.64.0)
Project-URL: Repository, https://github.com/remydubois/lsnms
